LICENSE
MANIFEST.in
README.rst
setup.py
src/vpoller-client
src/vpoller-proxy
src/vpoller-worker
src/vpoller/__init__.py
src/vpoller/client.py
src/vpoller/exceptions.py
src/vpoller/log.py
src/vpoller/proxy.py
src/vpoller/worker.py
src/vpoller.egg-info/PKG-INFO
src/vpoller.egg-info/SOURCES.txt
src/vpoller.egg-info/dependency_links.txt
src/vpoller.egg-info/requires.txt
src/vpoller.egg-info/top_level.txt
src/vpoller/helpers/__init__.py
src/vpoller/helpers/cclient.py
src/vpoller/helpers/csvhelper.py
src/vpoller/helpers/czabbix.py
src/vpoller/helpers/zabbix.py
src/vpoller/task/__init__.py
src/vpoller/task/core.py
src/vpoller/task/decorators.py
src/vpoller/task/registry.py
src/vpoller/vsphere/__init__.py
src/vpoller/vsphere/tasks.py