Metadata-Version: 1.1
Name: vpoller
Version: 0.7.3
Summary: Distributed VMware vSphere API Proxy
Home-page: https://github.com/dnaeon/py-vpoller
Author: Marin Atanasov Nikolov
Author-email: dnaeon@gmail.com
License: BSD
Download-URL: https://github.com/dnaeon/py-vpoller/releases
Platform: UNKNOWN
